aws_resource_monitor/__init__.py
aws_resource_monitor/monitor.py
aws_resource_monitor-1.0.0.dist-info/LICENSE
aws_resource_monitor-1.0.0.dist-info/METADATA
aws_resource_monitor-1.0.0.dist-info/WHEEL
aws_resource_monitor-1.0.0.dist-info/top_level.txt
aws_resource_monitor-1.0.0.dist-info/RECORD
