Metadata-Version: 2.1
Name: aws-resource-monitor
Version: 1.0.0
Summary: Easily monitor CPU and memory usage in AWS Batch jobs and report them to StatsD
Home-page: https://www.luigisbox.com/
Author: Luigi's Box
Author-email: support@luigisbox.com
License: MIT
Project-URL: Bug Tracker, https://github.com/luigisbox/aws-resource-monitor/issues
Project-URL: Source Code, https://github.com/palosopko/aws-resource-monitor
Keywords: aws monitoring
Platform: UNKNOWN
Classifier: Development Status :: 5 - Production/Stable
Classifier: Intended Audience :: Developers
Classifier: License :: OSI Approved :: MIT License
Classifier: Operating System :: OS Independent
Classifier: Programming Language :: Python
Classifier: Programming Language :: Python :: 3
Classifier: Programming Language :: Python :: 3 :: Only
Classifier: Programming Language :: Python :: 3.5
Classifier: Programming Language :: Python :: 3.6
Classifier: Programming Language :: Python :: 3.7
Classifier: Programming Language :: Python :: Implementation :: PyPy
Classifier: Topic :: Software Development :: Libraries
Classifier: Topic :: Utilities
Requires-Python: >=3.5
